README.rst
res.py
setup.py
spritify.py
spritify.egg-info/PKG-INFO
spritify.egg-info/SOURCES.txt
spritify.egg-info/dependency_links.txt
spritify.egg-info/requires.txt
spritify.egg-info/top_level.txt