Metadata-Version: 1.1
Name: spritify
Version: 0.4.2
Summary: The spritify is a tool for transform directory of images in the stylesheet and image file.
Home-page: UNKNOWN
Author: Rodrigo Pinheiro Matias
Author-email: rodrigopmatias@gmail.com
License: UNKNOWN
Platform: UNKNOWN
Classifier: Development Status :: 5 - Production/Stable
Classifier: Environment :: Web Environment
Classifier: Intended Audience :: Developers
Classifier: Intended Audience :: Information Technology
Classifier: License :: OSI Approved :: Apache Software License
Classifier: Natural Language :: Portuguese (Brazilian)
Classifier: Operating System :: POSIX
Classifier: Programming Language :: Python
Classifier: Programming Language :: Python :: 2.4
Classifier: Programming Language :: Python :: 2.5
Classifier: Programming Language :: Python :: 2.6
Classifier: Programming Language :: Python :: 2.7
Classifier: Topic :: Internet
Classifier: Topic :: Multimedia :: Graphics :: Editors
Classifier: Topic :: Software Development :: Code Generators
Classifier: Topic :: Text Processing :: Markup :: HTML
